spiderfoot_client/__init__.py
spiderfoot_client/cli.py
spiderfoot_client/client.py
spiderfoot_client-1.0.0.dist-info/licenses/LICENSE
spiderfoot_client-1.0.0.dist-info/METADATA
spiderfoot_client-1.0.0.dist-info/WHEEL
spiderfoot_client-1.0.0.dist-info/entry_points.txt
spiderfoot_client-1.0.0.dist-info/top_level.txt
spiderfoot_client-1.0.0.dist-info/RECORD
