Metadata-Version: 2.4
Name: spiderfoot-client
Version: 1.0.0
Summary: Python client library for SpiderFoot API
Author-email: Vlatko Kosturjak <vlatko.kosturjak@marlink.com>
License: MIT
Project-URL: Homepage, https://github.com/marlinkcyber/spiderfoot-client
Project-URL: Repository, https://github.com/marlinkcyber/spiderfoot-client
Project-URL: Documentation, https://github.com/marlinkcyber/spiderfoot-client
Project-URL: Bug Tracker, https://github.com/marlinkcyber/spiderfoot-client/issues
Keywords: spiderfoot,osint,security,reconnaissance,api
Classifier: Development Status :: 4 - Beta
Classifier: Intended Audience :: Developers
Classifier: Intended Audience :: Information Technology
Classifier: License :: OSI Approved :: MIT License
Classifier: Programming Language :: Python :: 3
Classifier: Programming Language :: Python :: 3.8
Classifier: Programming Language :: Python :: 3.9
Classifier: Programming Language :: Python :: 3.10
Classifier: Programming Language :: Python :: 3.11
Classifier: Programming Language :: Python :: 3.12
Classifier: Topic :: Security
Classifier: Topic :: Software Development :: Libraries :: Python Modules
Requires-Python: >=3.8
License-File: LICENSE
Requires-Dist: requests>=2.31.0
Provides-Extra: dev
Requires-Dist: pytest>=7.0.0; extra == "dev"
Requires-Dist: pytest-cov>=4.0.0; extra == "dev"
Requires-Dist: black>=23.0.0; extra == "dev"
Requires-Dist: flake8>=6.0.0; extra == "dev"
Requires-Dist: mypy>=1.0.0; extra == "dev"
Requires-Dist: types-requests; extra == "dev"
Dynamic: license-file
